Workbook

Sheet Datos Base
A1: DATOS BASE DE COSTEO — Felpudos y Servicios
A2: Transcrito de notas de costeo manuscritas (fotos compartidas 2026-07-21). Celdas en amarillo/azul = valores base que alimentan las fórmulas del Cotizador. Ver supuestos y alertas en la pestaña 'Notas y Supuestos'.
A4: 1. FELPUDO DE VINILO CON LOGO (personalizado, marca base Confort Mat)
A5: Concepto | B5: Valor | C5: Unidad
A6: Costo material base | B6: 59.17 | C6: S//m²
A7: Costo material extra (ribete de recorte) | B7: 94.9 | C7: S//m
A8: Longitud extra si área < 1.00 m² | B8: 0.2 | C8: m
A9: Longitud extra si área ≥ 1.00 m² | B9: 0.3 | C9: m
A10: Mano de obra — componente fijo | B10: 80 | C10: S/
A11: Mano de obra — componente variable | B11: 37.04 | C11: S//m²
A12: Ajuste fijo de acabado (tapiz) | B12: 25 | C12: S/
A13: Margen sugerido | B13: 0.4
A16: 2. FELPUDO DE VINILO EN ROLLO (sin logo) — ancho fijo de rollo 1.20 m
A17: Marca | B17: Espesor | C17: Costo (S//m) | D17: Margen sugerido | E17: Precio venta (S//m)
A18: Multilop | B18: 12mm | C18: 94.9 | D18: 0.35 | E18: =ROUND(C18/(1-D18),2) | F18: Multilop 12mm
A19: Multilop | B19: 15mm | C19: 126.9 | D19: 0.35 | E19: =ROUND(C19/(1-D19),2) | F19: Multilop 15mm
A20: Paolo | B20: 12mm | C20: 50 | D20: 0.4 | E20: =ROUND(C20/(1-D20),2) | F20: Paolo 12mm
A21: Paolo | B21: 15mm | C21: 95 | D21: 0.4 | E21: =ROUND(C21/(1-D21),2) | F21: Paolo 15mm
A22: Q Rubber | B22: 13-14mm | C22: 71 | D22: 0.4 | E22: =ROUND(C22/(1-D22),2) | F22: Q Rubber 13-14mm
A25: 3. FELPUDOS MIXTOS (retienen polvo y secan, perfil de jebe — marca base Confort Mat)
A26: Concepto | B26: Valor | C26: Unidad
A27: Costo material | B27: 45 | C27: S//m²
A28: Costo perfil (ribete de jebe) | B28: 9 | C28: S//m
A29: Extra fijo sobre perímetro | B29: 0.24 | C29: m
A30: Mano de obra — componente fijo | B30: 20 | C30: S/
A31: Mano de obra — componente variable | B31: 16.67 | C31: S//m²
A32: Margen sugerido | B32: 0.33
A35: 4. PISO ANTIFATIGA
A36: Marca | B36: Espesor | C36: Costo (S//m²) | D36: Margen sugerido | E36: Precio ref. (1.50×0.90m)
A37: Paolo | B37: 9mm | C37: 37.04 | D37: 0.58 | E37: =ROUND(C37*1.35/(1-D37),2) | F37: Paolo 9mm
A38: Q Rubber | B38: 13mm | C38: 87.41 | D38: 0.41 | E38: =ROUND(C38*1.35/(1-D38),2) | F38: Q Rubber 13mm

Sheet Cotizador
A1: COTIZADOR — Felpudos y Servicios
A2: Llena solo las celdas amarillas. El precio sugerido se calcula automáticamente a partir de los datos de costeo de la pestaña 'Datos Base'. Revisa 'Notas y Supuestos' antes de usarlo para cotizar en firme.
A4: A. FELPUDO DE VINILO (personalizado con logo, o en rollo sin logo)
A5: Ancho (m) | B5: 1.2
A6: Alto / largo (m) | B6: 0.9
A7: ¿Lleva logo? | B7: Sí
A8: Si NO lleva logo — Marca y espesor del rollo | B8: Multilop 12mm
A9: Margen deseado (%) — vacío = usar el sugerido
A11: RESULTADOS
A12: Área (m²) | B12: =B5*B6
A13: Costo materiales (S/) | B13: =IF(B7="Sí", B12*'Datos Base'!$B$6 + IF(B12<1,'Datos Base'!$B$8,'Datos Base'!$B$9)*'Datos Base'!$B$7, B6*INDEX('Datos Base'!$C$18:$C$22,MATCH(B8,'Datos Base'!$F$18:$F$22,0)))
A14: Costo mano de obra (S/) | B14: =IF(B7="Sí", 'Datos Base'!$B$10 + 'Datos Base'!$B$11*B12, 0)
A15: Costo total (S/) | B15: =B13+B14
A16: Margen aplicado (%) | B16: =IF(B9<>"", B9, IF(B7="Sí", 'Datos Base'!$B$13, INDEX('Datos Base'!$D$18:$D$22,MATCH(B8,'Datos Base'!$F$18:$F$22,0))))
A17: Ajuste fijo de acabado (S/, solo con logo) | B17: =IF(B7="Sí",'Datos Base'!$B$12,0)
A18: PRECIO SUGERIDO (S/) | B18: =ROUND(B15/(1-B16)+B17,2)
A21: B. FELPUDOS MIXTOS
A22: Ancho (m) | B22: 1.2
A23: Alto / largo (m) | B23: 1
A24: Margen deseado (%) — vacío = usar el sugerido
A26: RESULTADOS
A27: Área (m²) | B27: =B22*B23
A28: Perímetro + extra (m) | B28: =2*(B22+B23)+'Datos Base'!$B$29
A29: Costo materiales (S/) | B29: =B27*'Datos Base'!$B$27+B28*'Datos Base'!$B$28
A30: Costo mano de obra (S/) | B30: ='Datos Base'!$B$30+'Datos Base'!$B$31*B27
A31: Costo total (S/) | B31: =B29+B30
A32: Margen aplicado (%) | B32: =IF(B24<>"",B24,'Datos Base'!$B$32)
A33: PRECIO SUGERIDO (S/) | B33: =ROUND(B31/(1-B32),2)
A36: C. PISO ANTIFATIGA
A37: Ancho (m) | B37: 1.5
A38: Alto / largo (m) | B38: 0.9
A39: Marca y espesor | B39: Paolo 9mm
A40: Margen deseado (%) — vacío = usar el sugerido
A42: RESULTADOS
A43: Área (m²) | B43: =B37*B38
A44: Costo por m² (S/) | B44: =INDEX('Datos Base'!$C$37:$C$38,MATCH(B39,'Datos Base'!$F$37:$F$38,0))
A45: Costo total (S/) | B45: =B43*B44
A46: Margen aplicado (%) | B46: =IF(B40<>"",B40,INDEX('Datos Base'!$D$37:$D$38,MATCH(B39,'Datos Base'!$F$37:$F$38,0)))
A47: PRECIO SUGERIDO (S/) | B47: =ROUND(B45/(1-B46),2)

Sheet Notas y Supuestos
A1: NOTAS Y SUPUESTOS
A4: FUENTE: 3 fotos de notas de costeo manuscritas compartidas por el usuario el 2026-07-21 (Felpudos Mixtos / Piso Antifatiga, Felpudo Vinilo con Logo, Felpudo Vinilo en Rollos). Las fotos no quedaron guardadas como archivo en este repo (se compartieron pegadas en el chat, no como adjunto) — si se quiere conservar el original, hay que reenviarlas como archivo adjunto.
A6: CÓMO SE DERIVARON LAS FÓRMULAS
A7: Los valores en 'Datos Base' se obtuvieron por ingeniería inversa de los 4 (con logo) y 3 (mixtos) ejemplos manuscritos, ajustando una relación lineal (Costo = fijo + variable × área). El ajuste coincide casi exacto con los ejemplos de 'con logo' (diferencias de centavos por redondeo manual). En 'mixtos' el ajuste es un poco menos preciso (solo 3 puntos de datos) — validar con más ejemplos reales antes de confiar en el resultado para cotizaciones grandes.
A9: SUPUESTOS A VALIDAR CON EL USUARIO
A10: 1. Longitud extra (ribete) en 'con logo': se asumió 0.20 m para áreas menores a 1.00 m² y 0.30 m para el resto, porque así calzan los 4 ejemplos dados. No está confirmado si la regla real depende del área, del ancho del logo, o de otra cosa — pedir más ejemplos con distintos tamaños de logo.
A11: 2. Ajuste fijo de acabado ('tapiz'): en las notas originales varía entre S/23 y S/25 según el ejemplo. Se usó S/25 como estándar en el cotizador — confirmar si esa variación fue error de redondeo o un criterio real (p.ej. tamaño de logo).
A12: 3. Paolo 15mm: en la sección de COSTOS de la foto 3 aparece como S/90.00, pero en la sección de VENTA el cálculo del precio (S/158.00) solo cuadra si el costo es S/95.00. Se usó S/95.00 (el que sí reproduce el precio de venta anotado) — confirmar cuál es el costo correcto.
A13: 4. Mano de obra de 'Felpudos Mixtos': interpolada linealmente con solo 3 puntos de datos (S/40, S/45, S/50 para 1.20, 1.60 y 1.80 m de ancho) — es la fórmula menos confiable del archivo.
A14: 5. Piso Antifatiga: solo hay 1 ejemplo de precio por marca/espesor (a 1.50×0.90m), así que el costo por m² es una simple división — no hay forma de confirmar si escala igual a otros tamaños.
A16: CÓMO USAR EL COTIZADOR
A17: En la pestaña 'Cotizador', llenar solo las celdas amarillas (ancho, alto, si lleva logo, marca/espesor cuando aplique, y margen deseado — dejar el margen en blanco para usar el sugerido). El precio se recalcula solo. Si se actualiza algún costo real (p.ej. sube el precio del rollo), actualizarlo en 'Datos Base' y todo el cotizador se ajusta automáticamente.
